{"conjectures_proved":[["(+2 ts_ph_Nat_0 Z)","ts_ph_Nat_0",{"secs":0,"nanos":171236}],["(<=2 ts_ph_Nat_0 ts_ph_Nat_0)","true",{"secs":0,"nanos":1282424}],["(S (+2 ts_ph_Nat_0 ts_ph_Nat_1))","(+2 ts_ph_Nat_0 (S ts_ph_Nat_1))",{"secs":0,"nanos":478813}],["(+2 ts_ph_Nat_1 ts_ph_Nat_0)","(+2 ts_ph_Nat_0 ts_ph_Nat_1)",{"secs":0,"nanos":257681}],["(<=2 ts_ph_Nat_0 (S ts_ph_Nat_0))","true",{"secs":0,"nanos":1589669}],["false","(<=2 (S ts_ph_Nat_0) ts_ph_Nat_0)",{"secs":0,"nanos":1551918}],["(+2 ?ts_ph_Nat_0 (+2 ?ts_ph_Nat_1 ?ts_ph_Nat_2))","(+2 ?ts_ph_Nat_1 (+2 ?ts_ph_Nat_0 ?ts_ph_Nat_2))",{"secs":0,"nanos":1152105}],["(<=2 (+2 ts_ph_Nat_0 ts_ph_Nat_1) ts_ph_Nat_0)","(<=2 ts_ph_Nat_1 Z)",{"secs":0,"nanos":5882680}],["true","(<=2 ts_ph_Nat_0 (+2 ts_ph_Nat_0 ts_ph_Nat_1))",{"secs":0,"nanos":4729873}],["(<=2 ts_ph_Nat_0 Z)","(<=2 (+2 ts_ph_Nat_0 ts_ph_Nat_0) Z)",{"secs":0,"nanos":4734181}],["(<=2 (S ?ts_ph_Nat_1) (+2 ?ts_ph_Nat_0 ?ts_ph_Nat_1))","(<=2 (S Z) ?ts_ph_Nat_0)",{"secs":0,"nanos":31470621}],["(<=2 (+2 ?ts_ph_Nat_0 ?ts_ph_Nat_1) (S ?ts_ph_Nat_1))","(<=2 ?ts_ph_Nat_0 (S Z))",{"secs":0,"nanos":40008681}],["(<=2 (+2 ts_ph_Nat_0 ts_ph_Nat_0) (S Z))","(<=2 ts_ph_Nat_0 Z)",{"secs":0,"nanos":38173805}],["(<=2 (S Z) (+2 ts_ph_Nat_0 ts_ph_Nat_0))","(<=2 (S Z) ts_ph_Nat_0)",{"secs":0,"nanos":5243452}]],"failed_proofs":[["(<=2 ts_ph_Nat_0 ts_ph_Nat_1)","(<=2 (+2 ts_ph_Nat_0 ts_ph_Nat_0) (+2 ts_ph_Nat_0 ts_ph_Nat_1))",{"secs":0,"nanos":8562027}],["(<=2 ts_ph_Nat_1 ts_ph_Nat_0)","(<=2 (+2 ts_ph_Nat_0 ts_ph_Nat_1) (+2 ts_ph_Nat_0 ts_ph_Nat_0))",{"secs":0,"nanos":6796331}]],"goals_proved":[],"failed_proofs_goals":[],"equiv_red_iterations":[[{"egraph_nodes":85,"egraph_classes":85,"applied":{"rule0":5,"rule1":2,"rule2":2,"rule3":17,"rule4":5,"rule5":6},"hook_time":6e-8,"search_time":0.000130308,"apply_time":0.000027703,"rebuild_time":0.000041169,"total_time":0.0001993,"data":null,"n_rebuilds":24,"stop_reason":null},{"egraph_nodes":99,"egraph_classes":62,"applied":{"rule3":17,"rule5":1,"rule6":3},"hook_time":4e-8,"search_time":0.000112064,"apply_time":0.000037521,"rebuild_time":0.000015811,"total_time":0.000165526,"data":null,"n_rebuilds":15,"stop_reason":null},{"egraph_nodes":120,"egraph_classes":62,"applied":{"rule3":17,"rule6":3},"hook_time":4e-8,"search_time":0.000114208,"apply_time":0.000038704,"rebuild_time":0.000013405,"total_time":0.000166437,"data":null,"n_rebuilds":14,"stop_reason":null},{"egraph_nodes":143,"egraph_classes":65,"applied":{"rule3":17,"rule6":5},"hook_time":3e-8,"search_time":0.000123405,"apply_time":0.00004735,"rebuild_time":0.00001575,"total_time":0.000186635,"data":null,"n_rebuilds":15,"stop_reason":null},{"egraph_nodes":168,"egraph_classes":68,"applied":{"rule3":17,"rule6":5},"hook_time":4e-8,"search_time":0.000134236,"apply_time":0.000055616,"rebuild_time":0.000016521,"total_time":0.000206493,"data":null,"n_rebuilds":15,"stop_reason":null},{"egraph_nodes":193,"egraph_classes":71,"applied":{"rule3":17,"rule6":5},"hook_time":4e-8,"search_time":0.000144195,"apply_time":0.000063521,"rebuild_time":0.000017072,"total_time":0.000224908,"data":null,"n_rebuilds":15,"stop_reason":null},{"egraph_nodes":218,"egraph_classes":74,"applied":{"rule3":17,"rule6":5},"hook_time":4e-8,"search_time":0.000156168,"apply_time":0.000085623,"rebuild_time":0.000016522,"total_time":0.000258433,"data":null,"n_rebuilds":15,"stop_reason":null},{"egraph_nodes":243,"egraph_classes":77,"applied":{"rule3":17,"rule6":5},"hook_time":4e-8,"search_time":0.000162891,"apply_time":0.000082847,"rebuild_time":0.000017413,"total_time":0.000263272,"data":null,"n_rebuilds":15,"stop_reason":null},{"egraph_nodes":268,"egraph_classes":80,"applied":{"rule3":17,"rule6":5},"hook_time":4e-8,"search_time":0.000183951,"apply_time":0.000091895,"rebuild_time":0.000018515,"total_time":0.000294492,"data":null,"n_rebuilds":15,"stop_reason":null},{"egraph_nodes":293,"egraph_classes":83,"applied":{"rule3":17,"rule6":5},"hook_time":4e-8,"search_time":0.000186555,"apply_time":0.000102445,"rebuild_time":0.000017994,"total_time":0.000307115,"data":null,"n_rebuilds":15,"stop_reason":null},{"egraph_nodes":318,"egraph_classes":86,"applied":{"rule3":17,"rule6":5},"hook_time":4.1e-8,"search_time":0.000197115,"apply_time":0.000105782,"rebuild_time":0.000019056,"total_time":0.000322074,"data":null,"n_rebuilds":15,"stop_reason":null},{"egraph_nodes":343,"egraph_classes":89,"applied":{"rule3":17,"rule6":5},"hook_time":4e-8,"search_time":0.000204079,"apply_time":0.000120289,"rebuild_time":0.000019668,"total_time":0.000344156,"data":null,"n_rebuilds":15,"stop_reason":null},{"egraph_nodes":368,"egraph_classes":92,"applied":{},"hook_time":0.0,"search_time":0.0,"apply_time":0.0,"rebuild_time":0.0,"total_time":0.0,"data":null,"n_rebuilds":0,"stop_reason":{"IterationLimit":12}}],[{"egraph_nodes":368,"egraph_classes":92,"applied":{"rule3":17,"rule6":5,"(+2 ?ts_ph_Nat_0 Z) => ?ts_ph_Nat_0":2},"hook_time":4e-8,"search_time":0.000229397,"apply_time":0.000126511,"rebuild_time":0.000034286,"total_time":0.000390314,"data":null,"n_rebuilds":19,"stop_reason":null},{"egraph_nodes":391,"egraph_classes":91,"applied":{"rule3":17,"rule6":7},"hook_time":4e-8,"search_time":0.000228075,"apply_time":0.000134006,"rebuild_time":0.000025638,"total_time":0.000387839,"data":null,"n_rebuilds":17,"stop_reason":null},{"egraph_nodes":418,"egraph_classes":94,"applied":{"rule3":17,"rule6":7},"hook_time":4e-8,"search_time":0.000240007,"apply_time":0.000142071,"rebuild_time":0.000027623,"total_time":0.000409831,"data":null,"n_rebuilds":17,"stop_reason":null},{"egraph_nodes":445,"egraph_classes":97,"applied":{},"hook_time":0.0,"search_time":0.0,"apply_time":0.0,"rebuild_time":0.0,"total_time":0.0,"data":null,"n_rebuilds":0,"stop_reason":{"IterationLimit":3}}],[{"egraph_nodes":445,"egraph_classes":97,"applied":{"rule3":17,"rule6":7,"(<=2 ?ts_ph_Nat_0 ?ts_ph_Nat_0) => true":2},"hook_time":4e-8,"search_time":0.000265676,"apply_time":0.000199651,"rebuild_time":0.000033845,"total_time":0.000499292,"data":null,"n_rebuilds":16,"stop_reason":null},{"egraph_nodes":470,"egraph_classes":96,"applied":{"rule3":17,"rule6":7},"hook_time":4e-8,"search_time":0.000268973,"apply_time":0.000166407,"rebuild_time":0.00002631,"total_time":0.000461811,"data":null,"n_rebuilds":15,"stop_reason":null},{"egraph_nodes":497,"egraph_classes":99,"applied":{"rule3":17,"rule6":7},"hook_time":4e-8,"search_time":0.000281978,"apply_time":0.000177488,"rebuild_time":0.00002624,"total_time":0.000485826,"data":null,"n_rebuilds":15,"stop_reason":null},{"egraph_nodes":524,"egraph_classes":102,"applied":{},"hook_time":0.0,"search_time":0.0,"apply_time":0.0,"rebuild_time":0.0,"total_time":0.0,"data":null,"n_rebuilds":0,"stop_reason":{"IterationLimit":3}}],[{"egraph_nodes":994,"egraph_classes":572,"applied":{"rule0":11,"rule1":5,"rule2":8,"rule3":147,"rule4":11,"rule5":63,"rule6":7,"(<=2 ?ts_ph_Nat_0 ?ts_ph_Nat_0) => true":6,"(+2 ?ts_ph_Nat_0 Z) => ?ts_ph_Nat_0":6},"hook_time":4e-8,"search_time":0.001027418,"apply_time":0.000329989,"rebuild_time":0.000286156,"total_time":0.001643683,"data":null,"n_rebuilds":200,"stop_reason":null},{"egraph_nodes":1150,"egraph_classes":464,"applied":{"rule3":147,"rule6":20},"hook_time":4e-8,"search_time":0.000973726,"apply_time":0.000381216,"rebuild_time":0.00012593,"total_time":0.001480992,"data":null,"n_rebuilds":135,"stop_reason":null},{"egraph_nodes":1323,"egraph_classes":470,"applied":{"rule3":147,"rule6":26},"hook_time":4.1e-8,"search_time":0.001029833,"apply_time":0.000444688,"rebuild_time":0.000133815,"total_time":0.001608456,"data":null,"n_rebuilds":135,"stop_reason":null},{"egraph_nodes":1503,"egraph_classes":477,"applied":{"rule3":147,"rule6":26},"hook_time":4e-8,"search_time":0.001101319,"apply_time":0.000535831,"rebuild_time":0.000140538,"total_time":0.001777808,"data":null,"n_rebuilds":133,"stop_reason":null},{"egraph_nodes":1683,"egraph_classes":484,"applied":{"rule6":26},"hook_time":4e-8,"search_time":0.001171232,"apply_time":0.000254385,"rebuild_time":0.000107565,"total_time":0.001533302,"data":null,"n_rebuilds":15,"stop_reason":null},{"egraph_nodes":1709,"egraph_classes":484,"applied":{"rule6":7},"hook_time":4e-8,"search_time":0.001097582,"apply_time":0.000253803,"rebuild_time":0.00007361,"total_time":0.001425116,"data":null,"n_rebuilds":6,"stop_reason":null},{"egraph_nodes":1716,"egraph_classes":484,"applied":{"rule6":7},"hook_time":4e-8,"search_time":0.001113693,"apply_time":0.000258843,"rebuild_time":0.00007319,"total_time":0.001445846,"data":null,"n_rebuilds":6,"stop_reason":null},{"egraph_nodes":1723,"egraph_classes":484,"applied":{"rule6":7},"hook_time":4e-8,"search_time":0.001128841,"apply_time":0.000259655,"rebuild_time":0.00007347,"total_time":0.001462087,"data":null,"n_rebuilds":6,"stop_reason":null},{"egraph_nodes":1730,"egraph_classes":484,"applied":{"rule6":7},"hook_time":4e-8,"search_time":0.001121828,"apply_time":0.000267149,"rebuild_time":0.0000737,"total_time":0.001462807,"data":null,"n_rebuilds":6,"stop_reason":null},{"egraph_nodes":1737,"egraph_classes":484,"applied":{"rule3":147,"rule6":7},"hook_time":4e-8,"search_time":0.001196951,"apply_time":0.000716706,"rebuild_time":0.000103728,"total_time":0.002017515,"data":null,"n_rebuilds":124,"stop_reason":null},{"egraph_nodes":1900,"egraph_classes":493,"applied":{"rule3":147,"rule6":30},"hook_time":4e-8,"search_time":0.001250684,"apply_time":0.000534569,"rebuild_time":0.000136229,"total_time":0.001921602,"data":null,"n_rebuilds":133,"stop_reason":null},{"egraph_nodes":2086,"egraph_classes":502,"applied":{"rule3":147,"rule6":30},"hook_time":4e-8,"search_time":0.001161143,"apply_time":0.000595825,"rebuild_time":0.000139656,"total_time":0.001896744,"data":null,"n_rebuilds":133,"stop_reason":null},{"egraph_nodes":2272,"egraph_classes":511,"applied":{},"hook_time":0.0,"search_time":0.0,"apply_time":0.0,"rebuild_time":0.0,"total_time":0.0,"data":null,"n_rebuilds":0,"stop_reason":{"IterationLimit":12}}],[{"egraph_nodes":2272,"egraph_classes":511,"applied":{"rule3":147,"rule6":30,"(+2 ?ts_ph_Nat_0 (S ?ts_ph_Nat_1)) => (S (+2 ?ts_ph_Nat_0 ?ts_ph_Nat_1))":57,"(S (+2 ?ts_ph_Nat_0 ?ts_ph_Nat_1)) => (+2 ?ts_ph_Nat_0 (S ?ts_ph_Nat_1))":198},"hook_time":4e-8,"search_time":0.001529615,"apply_time":0.001056232,"rebuild_time":0.000864308,"total_time":0.003450275,"data":null,"n_rebuilds":272,"stop_reason":null},{"egraph_nodes":2272,"egraph_classes":413,"applied":{"rule6":63,"(S (+2 ?ts_ph_Nat_0 ?ts_ph_Nat_1)) => (+2 ?ts_ph_Nat_0 (S ?ts_ph_Nat_1))":180},"hook_time":4e-8,"search_time":0.001456325,"apply_time":0.000526954,"rebuild_time":0.000501356,"total_time":0.002484755,"data":null,"n_rebuilds":108,"stop_reason":null},{"egraph_nodes":2515,"egraph_classes":413,"applied":{"rule6":25,"(S (+2 ?ts_ph_Nat_0 ?ts_ph_Nat_1)) => (+2 ?ts_ph_Nat_0 (S ?ts_ph_Nat_1))":163},"hook_time":4e-8,"search_time":0.001304326,"apply_time":0.000686869,"rebuild_time":0.000448535,"total_time":0.00243985,"data":null,"n_rebuilds":92,"stop_reason":null},{"egraph_nodes":2703,"egraph_classes":413,"applied":{},"hook_time":0.0,"search_time":0.0,"apply_time":0.0,"rebuild_time":0.0,"total_time":0.0,"data":null,"n_rebuilds":0,"stop_reason":{"IterationLimit":3}}],[{"egraph_nodes":2703,"egraph_classes":413,"applied":{"rule3":115,"rule6":26,"(+2 ?ts_ph_Nat_0 ?ts_ph_Nat_1) => (+2 ?ts_ph_Nat_1 ?ts_ph_Nat_0)":586,"(S (+2 ?ts_ph_Nat_0 ?ts_ph_Nat_1)) => (+2 ?ts_ph_Nat_0 (S ?ts_ph_Nat_1))":79},"hook_time":4e-8,"search_time":0.001885904,"apply_time":0.001846068,"rebuild_time":0.000815654,"total_time":0.004547756,"data":null,"n_rebuilds":242,"stop_reason":null},{"egraph_nodes":3137,"egraph_classes":312,"applied":{},"hook_time":4e-8,"search_time":0.002044586,"apply_time":0.0000212,"rebuild_time":0.000075294,"total_time":0.002142031,"data":null,"n_rebuilds":0,"stop_reason":null},{"egraph_nodes":3137,"egraph_classes":312,"applied":{"rule3":96,"rule6":215,"(+2 ?ts_ph_Nat_0 ?ts_ph_Nat_1) => (+2 ?ts_ph_Nat_1 ?ts_ph_Nat_0)":2,"(S (+2 ?ts_ph_Nat_0 ?ts_ph_Nat_1)) => (+2 ?ts_ph_Nat_0 (S ?ts_ph_Nat_1))":78},"hook_time":4e-8,"search_time":0.00205708,"apply_time":0.002566441,"rebuild_time":0.000308317,"total_time":0.004931968,"data":null,"n_rebuilds":123,"stop_reason":null},{"egraph_nodes":3534,"egraph_classes":318,"applied":{},"hook_time":0.0,"search_time":0.0,"apply_time":0.0,"rebuild_time":0.0,"total_time":0.0,"data":null,"n_rebuilds":0,"stop_reason":{"IterationLimit":3}}],[{"egraph_nodes":3534,"egraph_classes":318,"applied":{"rule3":96,"rule6":230,"(<=2 ?ts_ph_Nat_0 (S ?ts_ph_Nat_0)) => true":2,"(+2 ?ts_ph_Nat_0 ?ts_ph_Nat_1) => (+2 ?ts_ph_Nat_1 ?ts_ph_Nat_0)":2,"(S (+2 ?ts_ph_Nat_0 ?ts_ph_Nat_1)) => (+2 ?ts_ph_Nat_0 (S ?ts_ph_Nat_1))":75},"hook_time":4e-8,"search_time":0.002316685,"apply_time":0.002730834,"rebuild_time":0.000326432,"total_time":0.005374071,"data":null,"n_rebuilds":120,"stop_reason":null},{"egraph_nodes":3941,"egraph_classes":320,"applied":{},"hook_time":4e-8,"search_time":0.002632266,"apply_time":0.000027382,"rebuild_time":0.000088499,"total_time":0.00274978,"data":null,"n_rebuilds":0,"stop_reason":null},{"egraph_nodes":3941,"egraph_classes":320,"applied":{"rule3":96},"hook_time":4e-8,"search_time":0.002586208,"apply_time":0.001454472,"rebuild_time":0.000112214,"total_time":0.004153014,"data":null,"n_rebuilds":71,"stop_reason":null},{"egraph_nodes":4043,"egraph_classes":326,"applied":{},"hook_time":0.0,"search_time":0.0,"apply_time":0.0,"rebuild_time":0.0,"total_time":0.0,"data":null,"n_rebuilds":0,"stop_reason":{"IterationLimit":3}}],[{"egraph_nodes":4043,"egraph_classes":326,"applied":{"rule3":96,"rule6":245,"(<=2 (S ?ts_ph_Nat_0) ?ts_ph_Nat_0) => false":2,"(+2 ?ts_ph_Nat_0 ?ts_ph_Nat_1) => (+2 ?ts_ph_Nat_1 ?ts_ph_Nat_0)":2,"(S (+2 ?ts_ph_Nat_0 ?ts_ph_Nat_1)) => (+2 ?ts_ph_Nat_0 (S ?ts_ph_Nat_1))":71},"hook_time":3e-8,"search_time":0.00278639,"apply_time":0.003155253,"rebuild_time":0.000322805,"total_time":0.006264568,"data":null,"n_rebuilds":115,"stop_reason":null},{"egraph_nodes":4461,"egraph_classes":328,"applied":{},"hook_time":4e-8,"search_time":0.003088285,"apply_time":0.000033504,"rebuild_time":0.000097666,"total_time":0.003221338,"data":null,"n_rebuilds":0,"stop_reason":null},{"egraph_nodes":4461,"egraph_classes":328,"applied":{"rule3":96},"hook_time":4e-8,"search_time":0.00307515,"apply_time":0.000742735,"rebuild_time":0.00012064,"total_time":0.003938645,"data":null,"n_rebuilds":69,"stop_reason":null},{"egraph_nodes":4563,"egraph_classes":334,"applied":{},"hook_time":0.0,"search_time":0.0,"apply_time":0.0,"rebuild_time":0.0,"total_time":0.0,"data":null,"n_rebuilds":0,"stop_reason":{"IterationLimit":3}}],[{"egraph_nodes":4563,"egraph_classes":334,"applied":{"rule3":96,"rule6":260,"(+2 ?ts_ph_Nat_1 (+2 ?ts_ph_Nat_0 ?ts_ph_Nat_2)) => (+2 ?ts_ph_Nat_0 (+2 ?ts_ph_Nat_1 ?ts_ph_Nat_2))":401,"(S (+2 ?ts_ph_Nat_0 ?ts_ph_Nat_1)) => (+2 ?ts_ph_Nat_0 (S ?ts_ph_Nat_1))":20},"hook_time":4e-8,"search_time":0.005867472,"apply_time":0.015499155,"rebuild_time":0.000377149,"total_time":0.021743896,"data":null,"n_rebuilds":130,"stop_reason":null},{"egraph_nodes":5333,"egraph_classes":330,"applied":{},"hook_time":4e-8,"search_time":0.006881594,"apply_time":0.000037351,"rebuild_time":0.00010993,"total_time":0.007030638,"data":null,"n_rebuilds":0,"stop_reason":null},{"egraph_nodes":5333,"egraph_classes":330,"applied":{"rule3":96},"hook_time":4e-8,"search_time":0.006782234,"apply_time":0.000850591,"rebuild_time":0.000134326,"total_time":0.007767271,"data":null,"n_rebuilds":69,"stop_reason":null},{"egraph_nodes":5435,"egraph_classes":336,"applied":{},"hook_time":0.0,"search_time":0.0,"apply_time":0.0,"rebuild_time":0.0,"total_time":0.0,"data":null,"n_rebuilds":0,"stop_reason":{"IterationLimit":3}}],[{"egraph_nodes":5435,"egraph_classes":336,"applied":{"rule3":96,"rule6":285,"(<=2 (+2 ?ts_ph_Nat_0 ?ts_ph_Nat_1) ?ts_ph_Nat_0) => (<=2 ?ts_ph_Nat_1 Z)":5,"(+2 ?ts_ph_Nat_1 (+2 ?ts_ph_Nat_0 ?ts_ph_Nat_2)) => (+2 ?ts_ph_Nat_0 (+2 ?ts_ph_Nat_1 ?ts_ph_Nat_2))":142,"(+2 ?ts_ph_Nat_0 ?ts_ph_Nat_1) => (+2 ?ts_ph_Nat_1 ?ts_ph_Nat_0)":46,"(S (+2 ?ts_ph_Nat_0 ?ts_ph_Nat_1)) => (+2 ?ts_ph_Nat_0 (S ?ts_ph_Nat_1))":16},"hook_time":4e-8,"search_time":0.007739028,"apply_time":0.022767827,"rebuild_time":0.000288038,"total_time":0.030795013,"data":null,"n_rebuilds":104,"stop_reason":null},{"egraph_nodes":6022,"egraph_classes":333,"applied":{},"hook_time":4e-8,"search_time":0.008614947,"apply_time":0.000119518,"rebuild_time":0.00012068,"total_time":0.008857109,"data":null,"n_rebuilds":0,"stop_reason":null},{"egraph_nodes":6022,"egraph_classes":333,"applied":{},"hook_time":4e-8,"search_time":0.008566424,"apply_time":0.00038849,"rebuild_time":0.000121752,"total_time":0.009078681,"data":null,"n_rebuilds":0,"stop_reason":null},{"egraph_nodes":6022,"egraph_classes":333,"applied":{},"hook_time":0.0,"search_time":0.0,"apply_time":0.0,"rebuild_time":0.0,"total_time":0.0,"data":null,"n_rebuilds":0,"stop_reason":{"IterationLimit":3}}],[{"egraph_nodes":6022,"egraph_classes":333,"applied":{"rule3":96,"rule6":300,"(<=2 ?ts_ph_Nat_0 (+2 ?ts_ph_Nat_0 ?ts_ph_Nat_1)) => true":5,"(+2 ?ts_ph_Nat_1 (+2 ?ts_ph_Nat_0 ?ts_ph_Nat_2)) => (+2 ?ts_ph_Nat_0 (+2 ?ts_ph_Nat_1 ?ts_ph_Nat_2))":2,"(S (+2 ?ts_ph_Nat_0 ?ts_ph_Nat_1)) => (+2 ?ts_ph_Nat_0 (S ?ts_ph_Nat_1))":16},"hook_time":4e-8,"search_time":0.00943009,"apply_time":0.027050999,"rebuild_time":0.000233646,"total_time":0.036714855,"data":null,"n_rebuilds":71,"stop_reason":null},{"egraph_nodes":6438,"egraph_classes":330,"applied":{},"hook_time":4e-8,"search_time":0.01020652,"apply_time":0.000161017,"rebuild_time":0.000127744,"total_time":0.010497445,"data":null,"n_rebuilds":0,"stop_reason":null},{"egraph_nodes":6438,"egraph_classes":330,"applied":{},"hook_time":4e-8,"search_time":0.010248009,"apply_time":0.000158411,"rebuild_time":0.000128325,"total_time":0.010536729,"data":null,"n_rebuilds":0,"stop_reason":null},{"egraph_nodes":6438,"egraph_classes":330,"applied":{},"hook_time":0.0,"search_time":0.0,"apply_time":0.0,"rebuild_time":0.0,"total_time":0.0,"data":null,"n_rebuilds":0,"stop_reason":{"IterationLimit":3}}],[{"egraph_nodes":6438,"egraph_classes":330,"applied":{"rule3":96,"rule6":315,"(<=2 (+2 ?ts_ph_Nat_0 ?ts_ph_Nat_0) Z) => (<=2 ?ts_ph_Nat_0 Z)":2,"(<=2 ?ts_ph_Nat_0 Z) => (<=2 (+2 ?ts_ph_Nat_0 ?ts_ph_Nat_0) Z)":8,"(+2 ?ts_ph_Nat_1 (+2 ?ts_ph_Nat_0 ?ts_ph_Nat_2)) => (+2 ?ts_ph_Nat_0 (+2 ?ts_ph_Nat_1 ?ts_ph_Nat_2))":2,"(S (+2 ?ts_ph_Nat_0 ?ts_ph_Nat_1)) => (+2 ?ts_ph_Nat_0 (S ?ts_ph_Nat_1))":16},"hook_time":4e-8,"search_time":0.010607023,"apply_time":0.030217182,"rebuild_time":0.00023654,"total_time":0.041060876,"data":null,"n_rebuilds":70,"stop_reason":null},{"egraph_nodes":6879,"egraph_classes":332,"applied":{"(<=2 ?ts_ph_Nat_0 Z) => (<=2 (+2 ?ts_ph_Nat_0 ?ts_ph_Nat_0) Z)":8},"hook_time":3e-8,"search_time":0.011630934,"apply_time":0.000189411,"rebuild_time":0.000138023,"total_time":0.011958488,"data":null,"n_rebuilds":4,"stop_reason":null},{"egraph_nodes":6893,"egraph_classes":338,"applied":{"(<=2 ?ts_ph_Nat_0 Z) => (<=2 (+2 ?ts_ph_Nat_0 ?ts_ph_Nat_0) Z)":8},"hook_time":4e-8,"search_time":0.004445662,"apply_time":0.000185734,"rebuild_time":0.00013639,"total_time":0.004767906,"data":null,"n_rebuilds":4,"stop_reason":null},{"egraph_nodes":6907,"egraph_classes":344,"applied":{},"hook_time":0.0,"search_time":0.0,"apply_time":0.0,"rebuild_time":0.0,"total_time":0.0,"data":null,"n_rebuilds":0,"stop_reason":{"IterationLimit":3}}],[{"egraph_nodes":6907,"egraph_classes":344,"applied":{"rule3":120,"rule5":3,"rule6":330,"(<=2 (S ?ts_ph_Nat_1) (+2 ?ts_ph_Nat_0 ?ts_ph_Nat_1)) => (<=2 (S Z) ?ts_ph_Nat_0)":4,"(<=2 ?ts_ph_Nat_0 Z) => (<=2 (+2 ?ts_ph_Nat_0 ?ts_ph_Nat_0) Z)":8,"(+2 ?ts_ph_Nat_1 (+2 ?ts_ph_Nat_0 ?ts_ph_Nat_2)) => (+2 ?ts_ph_Nat_0 (+2 ?ts_ph_Nat_1 ?ts_ph_Nat_2))":54,"(+2 ?ts_ph_Nat_0 (S ?ts_ph_Nat_1)) => (S (+2 ?ts_ph_Nat_0 ?ts_ph_Nat_1))":3,"(S (+2 ?ts_ph_Nat_0 ?ts_ph_Nat_1)) => (+2 ?ts_ph_Nat_0 (S ?ts_ph_Nat_1))":16},"hook_time":4e-8,"search_time":0.012559363,"apply_time":0.035018391,"rebuild_time":0.0002626,"total_time":0.047840486,"data":null,"n_rebuilds":78,"stop_reason":null},{"egraph_nodes":7506,"egraph_classes":405,"applied":{"(<=2 ?ts_ph_Nat_0 Z) => (<=2 (+2 ?ts_ph_Nat_0 ?ts_ph_Nat_0) Z)":8},"hook_time":4e-8,"search_time":0.014159874,"apply_time":0.00038307,"rebuild_time":0.00015732,"total_time":0.014700384,"data":null,"n_rebuilds":4,"stop_reason":null},{"egraph_nodes":7522,"egraph_classes":413,"applied":{"(<=2 ?ts_ph_Nat_0 Z) => (<=2 (+2 ?ts_ph_Nat_0 ?ts_ph_Nat_0) Z)":8},"hook_time":3e-8,"search_time":0.006128008,"apply_time":0.000390113,"rebuild_time":0.000151769,"total_time":0.00667001,"data":null,"n_rebuilds":4,"stop_reason":null},{"egraph_nodes":7538,"egraph_classes":421,"applied":{},"hook_time":0.0,"search_time":0.0,"apply_time":0.0,"rebuild_time":0.0,"total_time":0.0,"data":null,"n_rebuilds":0,"stop_reason":{"IterationLimit":3}}],[{"egraph_nodes":7538,"egraph_classes":421,"applied":{"rule3":144,"rule5":59,"rule6":431,"(<=2 (+2 ?ts_ph_Nat_0 ?ts_ph_Nat_1) (S ?ts_ph_Nat_1)) => (<=2 ?ts_ph_Nat_0 (S Z))":4,"(<=2 ?ts_ph_Nat_0 Z) => (<=2 (+2 ?ts_ph_Nat_0 ?ts_ph_Nat_0) Z)":8,"(+2 ?ts_ph_Nat_1 (+2 ?ts_ph_Nat_0 ?ts_ph_Nat_2)) => (+2 ?ts_ph_Nat_0 (+2 ?ts_ph_Nat_1 ?ts_ph_Nat_2))":460,"(+2 ?ts_ph_Nat_0 (+2 ?ts_ph_Nat_1 ?ts_ph_Nat_2)) => (+2 ?ts_ph_Nat_1 (+2 ?ts_ph_Nat_0 ?ts_ph_Nat_2))":14,"(+2 ?ts_ph_Nat_0 ?ts_ph_Nat_1) => (+2 ?ts_ph_Nat_1 ?ts_ph_Nat_0)":49,"(+2 ?ts_ph_Nat_0 (S ?ts_ph_Nat_1)) => (S (+2 ?ts_ph_Nat_0 ?ts_ph_Nat_1))":19,"(S (+2 ?ts_ph_Nat_0 ?ts_ph_Nat_1)) => (+2 ?ts_ph_Nat_0 (S ?ts_ph_Nat_1))":76},"hook_time":4e-8,"search_time":0.015289135,"apply_time":0.039177096,"rebuild_time":0.000490375,"total_time":0.054956727,"data":null,"n_rebuilds":163,"stop_reason":null},{"egraph_nodes":8930,"egraph_classes":667,"applied":{"(<=2 ?ts_ph_Nat_0 Z) => (<=2 (+2 ?ts_ph_Nat_0 ?ts_ph_Nat_0) Z)":8},"hook_time":4e-8,"search_time":0.018481408,"apply_time":0.000619832,"rebuild_time":0.000195793,"total_time":0.019297163,"data":null,"n_rebuilds":4,"stop_reason":null},{"egraph_nodes":8946,"egraph_classes":675,"applied":{"(<=2 ?ts_ph_Nat_0 Z) => (<=2 (+2 ?ts_ph_Nat_0 ?ts_ph_Nat_0) Z)":8},"hook_time":4e-8,"search_time":0.008542258,"apply_time":0.000629631,"rebuild_time":0.000194651,"total_time":0.00936666,"data":null,"n_rebuilds":4,"stop_reason":null},{"egraph_nodes":8962,"egraph_classes":683,"applied":{},"hook_time":0.0,"search_time":0.0,"apply_time":0.0,"rebuild_time":0.0,"total_time":0.0,"data":null,"n_rebuilds":0,"stop_reason":{"IterationLimit":3}}],[{"egraph_nodes":8962,"egraph_classes":683,"applied":{"rule3":168,"rule5":386,"rule6":899,"(<=2 ?ts_ph_Nat_0 Z) => (<=2 (+2 ?ts_ph_Nat_0 ?ts_ph_Nat_0) (S Z))":82,"(<=2 ?ts_ph_Nat_0 Z) => (<=2 (+2 ?ts_ph_Nat_0 ?ts_ph_Nat_0) Z)":8,"(+2 ?ts_ph_Nat_1 (+2 ?ts_ph_Nat_0 ?ts_ph_Nat_2)) => (+2 ?ts_ph_Nat_0 (+2 ?ts_ph_Nat_1 ?ts_ph_Nat_2))":3142,"(+2 ?ts_ph_Nat_0 (+2 ?ts_ph_Nat_1 ?ts_ph_Nat_2)) => (+2 ?ts_ph_Nat_1 (+2 ?ts_ph_Nat_0 ?ts_ph_Nat_2))":243,"(+2 ?ts_ph_Nat_0 ?ts_ph_Nat_1) => (+2 ?ts_ph_Nat_1 ?ts_ph_Nat_0)":294,"(+2 ?ts_ph_Nat_0 (S ?ts_ph_Nat_1)) => (S (+2 ?ts_ph_Nat_0 ?ts_ph_Nat_1))":84,"(S (+2 ?ts_ph_Nat_0 ?ts_ph_Nat_1)) => (+2 ?ts_ph_Nat_0 (S ?ts_ph_Nat_1))":241},"hook_time":4e-8,"search_time":0.019369511,"apply_time":0.050423498,"rebuild_time":0.002331653,"total_time":0.072124792,"data":null,"n_rebuilds":448,"stop_reason":null},{"egraph_nodes":14210,"egraph_classes":1752,"applied":{"(<=2 ?ts_ph_Nat_0 Z) => (<=2 (+2 ?ts_ph_Nat_0 ?ts_ph_Nat_0) (S Z))":8,"(<=2 ?ts_ph_Nat_0 Z) => (<=2 (+2 ?ts_ph_Nat_0 ?ts_ph_Nat_0) Z)":8,"(<=2 (+2 ?ts_ph_Nat_0 ?ts_ph_Nat_1) ?ts_ph_Nat_0) => (<=2 ?ts_ph_Nat_1 Z)":22},"hook_time":4e-8,"search_time":0.031620817,"apply_time":0.000778594,"rebuild_time":0.000395503,"total_time":0.032795045,"data":null,"n_rebuilds":4,"stop_reason":null},{"egraph_nodes":14256,"egraph_classes":1760,"applied":{"(<=2 ?ts_ph_Nat_0 Z) => (<=2 (+2 ?ts_ph_Nat_0 ?ts_ph_Nat_0) (S Z))":30,"(<=2 ?ts_ph_Nat_0 Z) => (<=2 (+2 ?ts_ph_Nat_0 ?ts_ph_Nat_0) Z)":30},"hook_time":4e-8,"search_time":0.013318871,"apply_time":0.00079757,"rebuild_time":0.000385004,"total_time":0.014501565,"data":null,"n_rebuilds":4,"stop_reason":null},{"egraph_nodes":14334,"egraph_classes":1778,"applied":{},"hook_time":0.0,"search_time":0.0,"apply_time":0.0,"rebuild_time":0.0,"total_time":0.0,"data":null,"n_rebuilds":0,"stop_reason":{"IterationLimit":3}}],[{"egraph_nodes":14334,"egraph_classes":1778,"applied":{"rule2":127,"rule3":332,"rule5":2518,"rule6":2553,"(<=2 (S Z) ?ts_ph_Nat_0) => (<=2 (S Z) (+2 ?ts_ph_Nat_0 ?ts_ph_Nat_0))":16,"(<=2 ?ts_ph_Nat_0 Z) => (<=2 (+2 ?ts_ph_Nat_0 ?ts_ph_Nat_0) (S Z))":30,"(<=2 ?ts_ph_Nat_0 Z) => (<=2 (+2 ?ts_ph_Nat_0 ?ts_ph_Nat_0) Z)":30,"(+2 ?ts_ph_Nat_1 (+2 ?ts_ph_Nat_0 ?ts_ph_Nat_2)) => (+2 ?ts_ph_Nat_0 (+2 ?ts_ph_Nat_1 ?ts_ph_Nat_2))":21058,"(+2 ?ts_ph_Nat_0 (+2 ?ts_ph_Nat_1 ?ts_ph_Nat_2)) => (+2 ?ts_ph_Nat_1 (+2 ?ts_ph_Nat_0 ?ts_ph_Nat_2))":1068,"(+2 ?ts_ph_Nat_0 ?ts_ph_Nat_1) => (+2 ?ts_ph_Nat_1 ?ts_ph_Nat_0)":1388,"(+2 ?ts_ph_Nat_1 ?ts_ph_Nat_0) => (+2 ?ts_ph_Nat_0 ?ts_ph_Nat_1)":8,"(+2 ?ts_ph_Nat_0 (S ?ts_ph_Nat_1)) => (S (+2 ?ts_ph_Nat_0 ?ts_ph_Nat_1))":330,"(S (+2 ?ts_ph_Nat_0 ?ts_ph_Nat_1)) => (+2 ?ts_ph_Nat_0 (S ?ts_ph_Nat_1))":553},"hook_time":4e-8,"search_time":0.034392519,"apply_time":0.10636494,"rebuild_time":0.019292304,"total_time":0.160050034,"data":null,"n_rebuilds":1987,"stop_reason":null},{"egraph_nodes":37626,"egraph_classes":6009,"applied":{"(<=2 (S Z) ?ts_ph_Nat_0) => (<=2 (S Z) (+2 ?ts_ph_Nat_0 ?ts_ph_Nat_0))":14,"(<=2 ?ts_ph_Nat_0 Z) => (<=2 (+2 ?ts_ph_Nat_0 ?ts_ph_Nat_0) (S Z))":42,"(<=2 ?ts_ph_Nat_0 Z) => (<=2 (+2 ?ts_ph_Nat_0 ?ts_ph_Nat_0) Z)":42,"(+2 ?ts_ph_Nat_0 Z) => ?ts_ph_Nat_0":6},"hook_time":1.6e-7,"search_time":0.123315051,"apply_time":0.00084995,"rebuild_time":0.001494638,"total_time":0.125659859,"data":null,"n_rebuilds":14,"stop_reason":null},{"egraph_nodes":37752,"egraph_classes":6037,"applied":{"(<=2 (S Z) ?ts_ph_Nat_0) => (<=2 (S Z) (+2 ?ts_ph_Nat_0 ?ts_ph_Nat_0))":14,"(<=2 ?ts_ph_Nat_0 Z) => (<=2 (+2 ?ts_ph_Nat_0 ?ts_ph_Nat_0) (S Z))":42,"(<=2 ?ts_ph_Nat_0 Z) => (<=2 (+2 ?ts_ph_Nat_0 ?ts_ph_Nat_0) Z)":42},"hook_time":4e-8,"search_time":0.029274996,"apply_time":0.000748527,"rebuild_time":0.001197602,"total_time":0.031221265,"data":null,"n_rebuilds":8,"stop_reason":null},{"egraph_nodes":37893,"egraph_classes":6080,"applied":{},"hook_time":0.0,"search_time":0.0,"apply_time":0.0,"rebuild_time":0.0,"total_time":0.0,"data":null,"n_rebuilds":0,"stop_reason":{"IterationLimit":3}}]],"case_split":[],"term_creation":[[62,{"secs":0,"nanos":106843}],[470,{"secs":0,"nanos":713289}]],"get_conjectures":[{"secs":0,"nanos":428517},{"secs":0,"nanos":480055},{"secs":0,"nanos":541762},{"secs":0,"nanos":3647070},{"secs":0,"nanos":4725675},{"secs":0,"nanos":4984197},{"secs":0,"nanos":5582117},{"secs":0,"nanos":6253507},{"secs":0,"nanos":7315340},{"secs":0,"nanos":8063415},{"secs":0,"nanos":8561796},{"secs":0,"nanos":9259836},{"secs":0,"nanos":11003448},{"secs":0,"nanos":21586816},{"secs":1,"nanos":32954643},{"secs":36,"nanos":514446497}],"filtered_lemmas":[],"total_time":{"secs":38,"nanos":659327935},"measures":{},"start_total":{"secs_since_epoch":1611335050,"nanos_since_epoch":736820965}}