[[{"CaseSplitDepth":1},{"should_delete":{},"colors_sizes":{},"black_size":60,"vacuos_colors":[]}],[{"ProverBaseEnd":[{"name":"zero","params":[],"ret_type":{"nodes":[{"op":{"name":"Nat","index":"0"},"children":[]}]}},{"nodes":[{"op":{"name":"ts_ph_Nat_0","index":"57"},"children":[]},{"op":{"name":"ts_ph_Lst_1","index":"60"},"children":[]},{"op":{"name":"drop","index":"24"},"children":[0,1]},{"op":{"name":"rev","index":"31"},"children":[2]}]},{"nodes":[{"op":{"name":"ts_ph_Lst_1","index":"60"},"children":[]},{"op":{"name":"len","index":"21"},"children":[0]},{"op":{"name":"ts_ph_Nat_0","index":"57"},"children":[]},{"op":{"name":"minus","index":"11"},"children":[1,2]},{"op":{"name":"ts_ph_Lst_1","index":"60"},"children":[]},{"op":{"name":"rev","index":"31"},"children":[4]},{"op":{"name":"take","index":"28"},"children":[3,5]}]}]},{"should_delete":{},"colors_sizes":{},"black_size":8,"vacuos_colors":[]}],[{"CaseSplitDepth":1},{"should_delete":{},"colors_sizes":{},"black_size":58,"vacuos_colors":[]}],[{"ProverBaseEnd":[{"name":"nil","params":[],"ret_type":{"nodes":[{"op":{"name":"Lst","index":"1"},"children":[]}]}},{"nodes":[{"op":{"name":"ts_ph_Nat_1","index":"58"},"children":[]},{"op":{"name":"ts_ph_Lst_0","index":"59"},"children":[]},{"op":{"name":"drop","index":"24"},"children":[0,1]},{"op":{"name":"rev","index":"31"},"children":[2]}]},{"nodes":[{"op":{"name":"ts_ph_Lst_0","index":"59"},"children":[]},{"op":{"name":"len","index":"21"},"children":[0]},{"op":{"name":"ts_ph_Nat_1","index":"58"},"children":[]},{"op":{"name":"minus","index":"11"},"children":[1,2]},{"op":{"name":"ts_ph_Lst_0","index":"59"},"children":[]},{"op":{"name":"rev","index":"31"},"children":[4]},{"op":{"name":"take","index":"28"},"children":[3,5]}]}]},{"should_delete":{},"colors_sizes":{},"black_size":8,"vacuos_colors":[]}],[{"CaseSplitDepth":1},{"should_delete":{"0":0,"1":0},"colors_sizes":{"0":0,"1":0},"black_size":82,"vacuos_colors":[]}],[{"ProverIndEnd":[{"name":"cons","params":[{"nodes":[{"op":{"name":"Nat","index":"0"},"children":[]}]},{"nodes":[{"op":{"name":"Lst","index":"1"},"children":[]}]}],"ret_type":{"nodes":[{"op":{"name":"Lst","index":"1"},"children":[]}]}},{"nodes":[{"op":{"name":"ts_ph_Nat_1","index":"58"},"children":[]},{"op":{"name":"ts_ph_Lst_0","index":"59"},"children":[]},{"op":{"name":"drop","index":"24"},"children":[0,1]},{"op":{"name":"rev","index":"31"},"children":[2]}]},{"nodes":[{"op":{"name":"ts_ph_Lst_0","index":"59"},"children":[]},{"op":{"name":"len","index":"21"},"children":[0]},{"op":{"name":"ts_ph_Nat_1","index":"58"},"children":[]},{"op":{"name":"minus","index":"11"},"children":[1,2]},{"op":{"name":"ts_ph_Lst_0","index":"59"},"children":[]},{"op":{"name":"rev","index":"31"},"children":[4]},{"op":{"name":"take","index":"28"},"children":[3,5]}]}]},{"should_delete":{},"colors_sizes":{},"black_size":8,"vacuos_colors":[]}],["End",{"should_delete":{},"colors_sizes":{},"black_size":50,"vacuos_colors":[]}]]