{"conjectures_proved":[["(zip2 ts_ph_list4_0 nil4)","nil2",{"secs":0,"nanos":23313110}],["(zip ts_ph_list3_0 nil4)","nil",{"secs":0,"nanos":23551242}]],"failed_proofs":[],"goals_proved":[],"failed_proofs_goals":[],"equiv_red_iterations":[[{"egraph_nodes":168,"egraph_classes":168,"applied":{"rule0":5,"rule1":5,"rule2":2,"rule3":2,"rule6":2},"hook_time":7e-8,"search_time":0.000358041,"apply_time":0.000012915,"rebuild_time":0.0000161,"total_time":0.000387166,"data":null,"n_rebuilds":6,"stop_reason":null},{"egraph_nodes":170,"egraph_classes":154,"applied":{"rule7":6},"hook_time":4e-8,"search_time":0.000318195,"apply_time":0.000011422,"rebuild_time":0.000011792,"total_time":0.000341519,"data":null,"n_rebuilds":1,"stop_reason":null},{"egraph_nodes":180,"egraph_classes":158,"applied":{"rule7":6},"hook_time":4.1e-8,"search_time":0.000332852,"apply_time":0.000014728,"rebuild_time":0.000011432,"total_time":0.000359112,"data":null,"n_rebuilds":1,"stop_reason":null},{"egraph_nodes":190,"egraph_classes":162,"applied":{},"hook_time":4e-8,"search_time":0.000337301,"apply_time":0.000011872,"rebuild_time":0.000011081,"total_time":0.000360485,"data":null,"n_rebuilds":0,"stop_reason":null},{"egraph_nodes":190,"egraph_classes":162,"applied":{},"hook_time":0.0,"search_time":0.0,"apply_time":0.0,"rebuild_time":0.0,"total_time":0.0,"data":null,"n_rebuilds":0,"stop_reason":"Saturated"}],[{"egraph_nodes":198,"egraph_classes":166,"applied":{"rule7":2},"hook_time":5e-8,"search_time":0.000370304,"apply_time":0.00001575,"rebuild_time":0.000012143,"total_time":0.000398307,"data":null,"n_rebuilds":1,"stop_reason":null},{"egraph_nodes":200,"egraph_classes":166,"applied":{"rule7":2},"hook_time":5e-8,"search_time":0.000361988,"apply_time":0.00001593,"rebuild_time":0.000011773,"total_time":0.000389811,"data":null,"n_rebuilds":1,"stop_reason":null},{"egraph_nodes":202,"egraph_classes":166,"applied":{},"hook_time":4e-8,"search_time":0.000362169,"apply_time":0.000015209,"rebuild_time":0.000011542,"total_time":0.0003891,"data":null,"n_rebuilds":0,"stop_reason":null},{"egraph_nodes":202,"egraph_classes":166,"applied":{},"hook_time":0.0,"search_time":0.0,"apply_time":0.0,"rebuild_time":0.0,"total_time":0.0,"data":null,"n_rebuilds":0,"stop_reason":"Saturated"}],[{"egraph_nodes":1061,"egraph_classes":1025,"applied":{"rule0":10,"rule1":10,"rule2":21,"rule3":10,"rule4":192,"rule6":100},"hook_time":5e-8,"search_time":0.002296515,"apply_time":0.000256307,"rebuild_time":0.000132251,"total_time":0.002685193,"data":null,"n_rebuilds":192,"stop_reason":null},{"egraph_nodes":1206,"egraph_classes":827,"applied":{"rule5":706,"rule6":2,"rule7":380},"hook_time":4e-8,"search_time":0.002166958,"apply_time":0.001136029,"rebuild_time":0.000146418,"total_time":0.003449516,"data":null,"n_rebuilds":43,"stop_reason":null},{"egraph_nodes":2403,"egraph_classes":936,"applied":{"rule7":156},"hook_time":4e-8,"search_time":0.002804731,"apply_time":0.001065776,"rebuild_time":0.000109518,"total_time":0.003980145,"data":null,"n_rebuilds":7,"stop_reason":null},{"egraph_nodes":2589,"egraph_classes":966,"applied":{"rule7":192},"hook_time":5e-8,"search_time":0.002889542,"apply_time":0.001182066,"rebuild_time":0.000114687,"total_time":0.004186416,"data":null,"n_rebuilds":8,"stop_reason":null},{"egraph_nodes":2829,"egraph_classes":1014,"applied":{},"hook_time":4e-8,"search_time":0.003090655,"apply_time":0.001182778,"rebuild_time":0.000109929,"total_time":0.004383602,"data":null,"n_rebuilds":0,"stop_reason":null},{"egraph_nodes":2829,"egraph_classes":1014,"applied":{},"hook_time":0.0,"search_time":0.0,"apply_time":0.0,"rebuild_time":0.0,"total_time":0.0,"data":null,"n_rebuilds":0,"stop_reason":"Saturated"}]],"case_split":[[0,{"secs":0,"nanos":22658266}],[0,{"secs":0,"nanos":300636836}]],"term_creation":[[110,{"secs":0,"nanos":311812}],[859,{"secs":0,"nanos":2043925}]],"get_conjectures":[{"secs":0,"nanos":414809},{"secs":0,"nanos":411853},{"secs":0,"nanos":407294},{"secs":0,"nanos":7806137},{"secs":0,"nanos":7659237},{"secs":0,"nanos":7691248}],"filtered_lemmas":[],"total_time":{"secs":0,"nanos":364194266},"measures":{"8":{"start":{"secs_since_epoch":1612357654,"nanos_since_epoch":629929278},"amount":0},"2":{"start":{"secs_since_epoch":1612357654,"nanos_since_epoch":583607497},"amount":0}},"start_total":{"secs_since_epoch":1612357654,"nanos_since_epoch":581768131}}